evoml_pipeline_interface/__init__.py
evoml_pipeline_interface/py.typed
evoml_pipeline_interface/interfaces/__init__.py
evoml_pipeline_interface/interfaces/pipeline_handler_interface.py
evoml_pipeline_interface/models/__init__.py
evoml_pipeline_interface/models/pipeline_data_models.py
evoml_pipeline_interface/models/pipeline_structure_conf.py
turintech_evoml_pipeline_interface-2.4.0.dist-info/AUTHORS.md
turintech_evoml_pipeline_interface-2.4.0.dist-info/LICENSE
turintech_evoml_pipeline_interface-2.4.0.dist-info/METADATA
turintech_evoml_pipeline_interface-2.4.0.dist-info/WHEEL
turintech_evoml_pipeline_interface-2.4.0.dist-info/top_level.txt
turintech_evoml_pipeline_interface-2.4.0.dist-info/RECORD
