Metadata-Version: 2.1
Name: turintech-evoml-pipeline-interface
Version: 2.4.0
Summary: Library that contains the interface of the pipelines of the ML Models generated by evoml
Home-page: https://turintech.ai
Author: Turing Intelligence Technology
License: UNKNOWN
Keywords: EvoML pipeline interface
Platform: UNKNOWN
Classifier: Development Status :: 5 - Production/Stable
Classifier: Intended Audience :: Developers
Classifier: License :: Other/Proprietary License
Classifier: Programming Language :: Python :: 3.9
Classifier: Programming Language :: Python :: 3.10
Classifier: Programming Language :: Python :: 3.11
Requires-Python: >=3.9
License-File: LICENSE
License-File: AUTHORS.md
Requires-Dist: pydantic[dotenv]<2.0.0
Requires-Dist: pandas
Requires-Dist: joblib
Requires-Dist: loguru
Requires-Dist: turintech-evoml-api-models<4.0.0,>=3.1.0a0
Requires-Dist: turintech-evoml-utils<3.0.0,>=2.0.0a0
